uploader/__init__.py
uploader/upload.py
uploader/authentication/__init__.py
uploader/authentication/authentication.py
uploader/domain/__init__.py
uploader/domain/domain.py
uploader/domain/exceptions.py
uploader/domain/test_run.py
uploader/domain/ci/__init__.py
uploader/domain/ci/drone_ci_test_run.py
uploader/domain/ci/github_test_run.py
uploader/domain/ci/jenkins_test_run.py
uploader/receiver/__init__.py
uploader/receiver/receiver.py
uploader/utils/__init__.py
uploader/utils/urls.py
uploader/utils/utils.py
uploader/utils/zipper.py
testpulse_uploader-0.0.30.dist-info/LICENSE
testpulse_uploader-0.0.30.dist-info/METADATA
testpulse_uploader-0.0.30.dist-info/WHEEL
testpulse_uploader-0.0.30.dist-info/entry_points.txt
testpulse_uploader-0.0.30.dist-info/top_level.txt
testpulse_uploader-0.0.30.dist-info/RECORD
